r_functions.py
r_functions-1.0.3.dist-info/LICENSE
r_functions-1.0.3.dist-info/METADATA
r_functions-1.0.3.dist-info/WHEEL
r_functions-1.0.3.dist-info/top_level.txt
r_functions-1.0.3.dist-info/zip-safe
r_functions-1.0.3.dist-info/RECORD
