Metadata-Version: 2.1
Name: r-functions
Version: 1.0.3
Summary: A library for running R functions from a source file
Home-page: https://github.com/park-brian/r-functions
Author: re.public
Author-email: re.public@outlook.com
License: UNKNOWN
Keywords: R,function,wrapper,library,async
Platform: UNKNOWN
Classifier: Intended Audience :: Developers
Classifier: License :: OSI Approved :: MIT License
Classifier: Operating System :: OS Independent
Classifier: Programming Language :: Python
Classifier: Programming Language :: Python :: 3.6
Classifier: Programming Language :: Python :: 3.7
Classifier: Programming Language :: Python :: 3.8
Classifier: Programming Language :: Python :: 3.9
Classifier: Topic :: Software Development :: Libraries :: Python Modules
Requires-Python: >=3.6
